kfp_toolbox/__init__.py
kfp_toolbox/_version.py
kfp_toolbox/cli.py
kfp_toolbox/components.py
kfp_toolbox/decorators.py
kfp_toolbox/pipelines.py
kfp_toolbox-0.5.0.dist-info/METADATA
kfp_toolbox-0.5.0.dist-info/WHEEL
kfp_toolbox-0.5.0.dist-info/entry_points.txt
kfp_toolbox-0.5.0.dist-info/licenses/LICENSE
kfp_toolbox-0.5.0.dist-info/RECORD
