Metadata-Version: 2.1
Name: kfp-toolbox
Version: 0.5.0
Summary: The toolbox for kfp (Kubeflow Pipelines SDK)
Project-URL: Homepage, https://speg03.github.io/kfp-toolbox/
Project-URL: Repository, https://github.com/speg03/kfp-toolbox
Author-email: Takahiro Yano <speg03@gmail.com>
License-File: LICENSE
Keywords: kfp,kubeflow,pipelines
Classifier: Development Status :: 4 - Beta
Classifier: Environment :: Console
Classifier: Intended Audience :: Developers
Classifier: License :: OSI Approved :: MIT License
Classifier: Operating System :: OS Independent
Classifier: Programming Language :: Python :: 3.7
Classifier: Programming Language :: Python :: 3.8
Classifier: Programming Language :: Python :: 3.9
Classifier: Programming Language :: Python :: 3.10
Classifier: Topic :: Software Development :: Libraries :: Python Modules
Requires-Python: >=3.7
Requires-Dist: google-cloud-aiplatform~=1.15
Requires-Dist: kfp~=1.8
Requires-Dist: pyyaml>=5.3
Requires-Dist: typer<1.0,>=0.4
Provides-Extra: docs
Requires-Dist: furo; extra == 'docs'
Requires-Dist: sphinx; extra == 'docs'
Requires-Dist: sphinx-autobuild; extra == 'docs'
Provides-Extra: tests
Requires-Dist: freezegun; extra == 'tests'
Requires-Dist: pytest; extra == 'tests'
Requires-Dist: pytest-cov; extra == 'tests'
